mcp_metaso/__init__.py
mcp_metaso/__main__.py
mcp_metaso/cli.py
mcp_metaso/config.py
mcp_metaso/formatters.py
mcp_metaso/server.py
mcp_metaso/tests.py
mcp_metaso/utils.py
mcp_metaso-0.2.0.dist-info/METADATA
mcp_metaso-0.2.0.dist-info/WHEEL
mcp_metaso-0.2.0.dist-info/entry_points.txt
mcp_metaso-0.2.0.dist-info/licenses/LICENSE
mcp_metaso-0.2.0.dist-info/RECORD
