Metadata-Version: 2.4
Name: mcp-metaso
Version: 0.2.0
Summary: 基于MCP协议的Metaso AI搜索引擎服务器
Project-URL: Homepage, https://github.com/HundunOnline/mcp-metaso
Project-URL: Repository, https://github.com/HundunOnline/mcp-metaso.git
Project-URL: Issues, https://github.com/HundunOnline/mcp-metaso/issues
Project-URL: Documentation, https://github.com/HundunOnline/mcp-metaso#readme
Author-email: MCP Metaso Team <support@example.com>
License-File: LICENSE
Keywords: ai,mcp,metaso,protocol,search
Classifier: Development Status :: 4 - Beta
Classifier: Intended Audience :: Developers
Classifier: License :: OSI Approved :: MIT License
Classifier: Programming Language :: Python :: 3
Classifier: Programming Language :: Python :: 3.11
Classifier: Programming Language :: Python :: 3.12
Classifier: Topic :: Internet :: WWW/HTTP :: Indexing/Search
Classifier: Topic :: Software Development :: Libraries :: Python Modules
Requires-Python: >=3.11
Requires-Dist: httpx>=0.28.1
Requires-Dist: mcp[cli]>=1.12.2
Provides-Extra: dev
Requires-Dist: black>=23.0; extra == 'dev'
Requires-Dist: isort>=5.12; extra == 'dev'
Requires-Dist: mypy>=1.0; extra == 'dev'
Requires-Dist: pytest-asyncio>=0.21.0; extra == 'dev'
Requires-Dist: pytest>=7.0; extra == 'dev'
